sc_leflib/__init__.py
sc_leflib/_leflib.cpython-314-x86_64-linux-gnu.so
sc_leflib-0.5.1.dist-info/METADATA
sc_leflib-0.5.1.dist-info/WHEEL
sc_leflib-0.5.1.dist-info/top_level.txt
sc_leflib-0.5.1.dist-info/RECORD
sc_leflib-0.5.1.dist-info/licenses/LICENSE
