Metadata-Version: 2.4
Name: sc-leflib
Version: 0.5.1
Summary: LEF parser for SiliconCompiler
Home-page: https://siliconcompiler.com
Author: ZeroASIC
Author-email: gadfort@zeroasic.com
License: Apache License 2.0
Project-URL: Documentation, https://docs.siliconcompiler.com
Project-URL: Source Code, https://github.com/siliconcompiler/sc-leflib
Project-URL: Bug Tracker, https://github.com/siliconcompiler/sc-leflib/issues
Project-URL: Forum, https://github.com/siliconcompiler/sc-leflib/discussions
Requires-Python: >=3.9
License-File: LICENSE
Provides-Extra: test
Requires-Dist: pytest==8.4.2; extra == "test"
Requires-Dist: pytest-timeout==2.4.0; extra == "test"
Requires-Dist: flake8==7.1.2; python_version <= "3.8" and extra == "test"
Requires-Dist: flake8==7.3.0; python_version >= "3.9" and extra == "test"
Dynamic: author
Dynamic: author-email
Dynamic: description
Dynamic: description-content-type
Dynamic: home-page
Dynamic: license
Dynamic: license-file
Dynamic: project-url
Dynamic: provides-extra
Dynamic: requires-python
Dynamic: summary
